torch_legendre/__init__.py
torch_legendre/_version.py
torch_legendre/legendre.py
torch_legendre-0.1.1.dist-info/licenses/LICENSE
torch_legendre-0.1.1.dist-info/METADATA
torch_legendre-0.1.1.dist-info/WHEEL
torch_legendre-0.1.1.dist-info/top_level.txt
torch_legendre-0.1.1.dist-info/RECORD
