Metadata-Version: 2.4
Name: torch_legendre
Version: 0.1.1
Summary: A Legendre Polynomial Layer for PyTorch
Author-email: Philipp Benner <philipp.benner@bam.de>
License-Expression: MIT
Keywords: machine learning
Classifier: Programming Language :: Python :: 3
Classifier: Operating System :: OS Independent
Requires-Python: >=3.9
License-File: LICENSE
Requires-Dist: torch
Provides-Extra: dev
Requires-Dist: mypy==1.0.1; extra == "dev"
Requires-Dist: ruff; extra == "dev"
Requires-Dist: matplotlib; extra == "dev"
Requires-Dist: pytest; extra == "dev"
Provides-Extra: docu
Requires-Dist: mkdocs; extra == "docu"
Requires-Dist: mkdocs-material; extra == "docu"
Requires-Dist: pymdown-extensions; extra == "docu"
Requires-Dist: mkdocs-click; extra == "docu"
Dynamic: license-file
